LICENSE
MANIFEST.in
README.rst
setup.py
docs/Note.md
drf_role/__init__.py
drf_role/apps.py
drf_role/enums.py
drf_role/models.py
drf_role/permissions.py
drf_role/serializers.py
drf_role/tests.py
drf_role/urls.py
drf_role/views.py
drf_role.egg-info/PKG-INFO
drf_role.egg-info/SOURCES.txt
drf_role.egg-info/dependency_links.txt
drf_role.egg-info/top_level.txt
drf_role/management/__init__.py
drf_role/management/commands/__init__.py
drf_role/management/commands/role_init.py
drf_role/migrations/0001_initial.py
drf_role/migrations/__init__.py
drf_role/tests/__init__.py
drf_role/tests/role_permission_tests.py
drf_role/utils/__init__.py
drf_role/utils/url_utilities.py